eSim/__init__.py
eSim/bot.py
eSim/login.py
eSim/Basic/__init__.py
eSim/Basic/accept_contract.py
eSim/Basic/battle_order.py
eSim/Basic/bid.py
eSim/Basic/buff.py
eSim/Basic/buy_cc.py
eSim/Basic/buy_product.py
eSim/Basic/candidate.py
eSim/Basic/change_avatar.py
eSim/Basic/comment_article.py
eSim/Basic/comment_shout.py
eSim/Basic/donate_eqs.py
eSim/Basic/eqs.py
eSim/Basic/fly.py
eSim/Basic/inventory.py
eSim/Basic/job.py
eSim/Basic/login.py
eSim/Basic/mpp_dow_attack.py
eSim/Basic/mu_inventory.py
eSim/Basic/place_building.py
eSim/Basic/read.py
eSim/Basic/register.py
eSim/Basic/report_citizen.py
eSim/Basic/reshuffle_or_upgrade.py
eSim/Basic/rw.py
eSim/Basic/sell_eqs.py
eSim/Basic/send_application.py
eSim/Basic/send_msg.py
eSim/Basic/shout.py
eSim/Basic/sub.py
eSim/Basic/use.py
eSim/Basic/vote_article.py
eSim/Basic/vote_elections.py
eSim/Basic/vote_law.py
eSim/Basic/vote_shout.py
eSim/Basic/wear_unwear.py
eSim/Fight/__init__.py
eSim/Fight/auto_fight.py
eSim/Fight/fight.py
eSim/Fight/hunt.py
eSim/Fight/hunt_specific_battle.py
eSim/Fight/login.py
eSim/Fight/motivates.py
eSim/Fight/supply.py
eSim/Fight/watch.py
eSim/Help_functions/__init__.py
eSim/Help_functions/bot_functions.py
eSim/Help_functions/install_packets.py
eSim/Help_functions/login.py
eSim/Time_saver/__init__.py
eSim/Time_saver/add_friends.py
eSim/Time_saver/bid_all_auctions.py
eSim/Time_saver/login.py
eSim/Time_saver/merge_storage.py
eSim/Time_saver/missions.py
eSim/Time_saver/msg_to_entire_server.py
eSim/Time_saver/sell_coins.py
eSim/Time_saver/sell_product_all_markets.py
eSim/Time_saver/send_contracts.py
eSim/Time_saver/utils.py
eSim-2.8.5.dist-info/LICENSE
eSim-2.8.5.dist-info/METADATA
eSim-2.8.5.dist-info/WHEEL
eSim-2.8.5.dist-info/top_level.txt
eSim-2.8.5.dist-info/RECORD
