Metadata-Version: 2.1
Name: eSim
Version: 2.8.5
Summary: E-sim python library
Home-page: https://github.com/e-sim-python/scripts
Author: e-sim-python
License: UNKNOWN
Platform: UNKNOWN
Classifier: Programming Language :: Python :: 3
Classifier: License :: OSI Approved :: GNU General Public License v3 (GPLv3)
Classifier: Operating System :: OS Independent
Requires-Python: >=3.6
Requires-Dist: lxml
Requires-Dist: discord.py
Requires-Dist: pytz
Requires-Dist: aiohttp
